betpy/__init__.py
betpy/bankroll.py
betpy/dfs.py
betpy/elo.py
betpy/odds.py
betpy/parlays.py
betpy/strategy/__init__.py
betpy/strategy/decision_function.py
betpy/strategy/sizing.py
betpy-0.0.1.dist-info/licenses/LICENSE
betpy-0.0.1.dist-info/METADATA
betpy-0.0.1.dist-info/WHEEL
betpy-0.0.1.dist-info/top_level.txt
betpy-0.0.1.dist-info/RECORD
