Metadata-Version: 2.4
Name: betpy
Version: 0.0.1
Summary: Odds utilities
Home-page: https://github.com/predicting-stuff/betpy
Author: Bryan Brzycki
Author-email: bryan@bryanbrzycki.com
Classifier: Programming Language :: Python :: 3
Classifier: License :: OSI Approved :: MIT License
Classifier: Operating System :: OS Independent
License-File: LICENSE
Requires-Dist: numpy
Requires-Dist: pandas
Requires-Dist: scikit-learn
Requires-Dist: mip
Requires-Dist: matplotlib
Requires-Dist: seaborn
Dynamic: author
Dynamic: author-email
Dynamic: classifier
Dynamic: description
Dynamic: description-content-type
Dynamic: home-page
Dynamic: license-file
Dynamic: requires-dist
Dynamic: summary
